httpie_nsof.py
httpie_nsof-1.7.data/scripts/httpie-nsof-setup
httpie_nsof-1.7.dist-info/DESCRIPTION.rst
httpie_nsof-1.7.dist-info/METADATA
httpie_nsof-1.7.dist-info/RECORD
httpie_nsof-1.7.dist-info/WHEEL
httpie_nsof-1.7.dist-info/entry_points.txt
httpie_nsof-1.7.dist-info/metadata.json
httpie_nsof-1.7.dist-info/top_level.txt
