Metadata-Version: 2.0
Name: httpie-nsof
Version: 1.7
Summary: Nsof OAuth 2 plugin for HTTPie.
Home-page: https://github.com/nsofnetworks/httpie-nsof
Author: Alon Horowitz
Author-email: alon@nsof.io
License: Apache License 2.0
Download-URL: https://github.com/nsofnetworks/httpie-nsof/archive/1.7.tar.gz
Keywords: httpie oauth oauth2 nsof token
Platform: UNKNOWN
Classifier: Development Status :: 5 - Production/Stable
Classifier: Programming Language :: Python
Classifier: Environment :: Plugins
Classifier: License :: OSI Approved :: Apache Software License
Classifier: Topic :: Internet :: WWW/HTTP
Classifier: Topic :: Utilities
Requires-Dist: httpie (>=0.7.0)
